sanctify/__init__.py
sanctify/cleanser.py
sanctify/constants.py
sanctify/exception.py
sanctify/processor.py
sanctify/serializer.py
sanctify/transformer.py
sanctify/utils.py
sanctify/validator.py
sanctify/examples/__init__.py
sanctify/examples/column_mapping_schema.py
sanctify/examples/data_type_schema.py
sanctify-1.5.4.dist-info/licenses/LICENSE
sanctify-1.5.4.dist-info/METADATA
sanctify-1.5.4.dist-info/WHEEL
sanctify-1.5.4.dist-info/top_level.txt
sanctify-1.5.4.dist-info/RECORD
