Metadata-Version: 2.4
Name: sanctify
Version: 1.5.4
Summary: Column Mapping based cleansing and validations for a given pandas dataframe
Author-email: Avijeet Diwaker <avijeetdiwaker@gmail.com>, Awadhesh Pratap <awadheshpratap@skit.ai>
Project-URL: Homepage, https://github.com/skit-ai/sanctify
Project-URL: Bug Tracker, https://github.com/skit-ai/sanctify/issues
Classifier: Development Status :: 5 - Production/Stable
Classifier: Intended Audience :: Developers
Classifier: License :: OSI Approved :: Apache Software License
Classifier: Programming Language :: Python :: 3.11
Requires-Python: >=3.11
License-File: LICENSE
Requires-Dist: dnspython>=2.0
Requires-Dist: email-validator==2.0.0.post2
Requires-Dist: frozendict>=2.3.8
Requires-Dist: idna==3.7
Requires-Dist: iniconfig==2.0.0
Requires-Dist: loguru>=0.6.0
Requires-Dist: numpy>=1.25
Requires-Dist: packaging==23.1
Requires-Dist: pandas>=2.0
Requires-Dist: phonenumbers==8.13.15
Requires-Dist: pluggy==1.2.0
Requires-Dist: pytest==7.4.0
Requires-Dist: python-dateutil==2.8.2
Requires-Dist: pytz>=2020.3
Requires-Dist: six==1.16.0
Requires-Dist: tzdata==2023.3
Requires-Dist: demoji>=1.1.0
Dynamic: license-file
